{"errors":[],"warnings":[],"namedChunkGroups":{"app":{"chunks":[6,0,2],"assets":["webpack-runtime-bcf9b0bd628a4b37f4fd.js","webpack-runtime-bcf9b0bd628a4b37f4fd.js.map","commons-78c0c05bbf470ed82300.js","commons-78c0c05bbf470ed82300.js.map","app-34c546cd701e32444a9c.js","app-34c546cd701e32444a9c.js.map"],"children":{},"childAssets":{}},"component---src-templates-learn-tsx":{"chunks":[1,0,5],"assets":["styles.04de800b1bd45638016e.css","styles-23dce91be698cf97c1eb.js","styles-23dce91be698cf97c1eb.js.map","commons-78c0c05bbf470ed82300.js","commons-78c0c05bbf470ed82300.js.map","component---src-templates-learn-tsx-7265a49399c6d414bda6.js","component---src-templates-learn-tsx-7265a49399c6d414bda6.js.map"],"children":{},"childAssets":{}},"component---src-pages-404-tsx":{"chunks":[1,0,3],"assets":["styles.04de800b1bd45638016e.css","styles-23dce91be698cf97c1eb.js","styles-23dce91be698cf97c1eb.js.map","commons-78c0c05bbf470ed82300.js","commons-78c0c05bbf470ed82300.js.map","component---src-pages-404-tsx-b23d78b4eafe093754af.js","component---src-pages-404-tsx-b23d78b4eafe093754af.js.map"],"children":{},"childAssets":{}},"component---src-pages-index-tsx":{"chunks":[1,0,4],"assets":["styles.04de800b1bd45638016e.css","styles-23dce91be698cf97c1eb.js","styles-23dce91be698cf97c1eb.js.map","commons-78c0c05bbf470ed82300.js","commons-78c0c05bbf470ed82300.js.map","component---src-pages-index-tsx-1b32e44e56fd74ac1abc.js","component---src-pages-index-tsx-1b32e44e56fd74ac1abc.js.map"],"children":{},"childAssets":{}}},"assetsByChunkName":{"app":["webpack-runtime-bcf9b0bd628a4b37f4fd.js","commons-78c0c05bbf470ed82300.js","app-34c546cd701e32444a9c.js"],"component---src-templates-learn-tsx":["styles.04de800b1bd45638016e.css","styles-23dce91be698cf97c1eb.js","commons-78c0c05bbf470ed82300.js","component---src-templates-learn-tsx-7265a49399c6d414bda6.js"],"component---src-pages-404-tsx":["styles.04de800b1bd45638016e.css","styles-23dce91be698cf97c1eb.js","commons-78c0c05bbf470ed82300.js","component---src-pages-404-tsx-b23d78b4eafe093754af.js"],"component---src-pages-index-tsx":["styles.04de800b1bd45638016e.css","styles-23dce91be698cf97c1eb.js","commons-78c0c05bbf470ed82300.js","component---src-pages-index-tsx-1b32e44e56fd74ac1abc.js"]}}